{"cssstudy_transition.md":"yM8RHhpt","cssstudy_z-index.md":"7Z2MdUKO","components_button_levitationanimation_001_001.md":"-d_KNT0w","cssstudy.md":"DzqSGBcK","author.md":"Uk6I9JpW","cssstudy_position.md":"iku8Ax1h","components_card_theme.md":"mprCJvt7","jstsstudy.md":"DIvLXEJz","components_card_001_001.md":"H2MJh0ec","components_button_onclick_index.md":"SzGbLtn6","components_card_index.md":"5KztirTn","components_menu_001_001.md":"yep73YVg","components_text_001_001.md":"UiRtDwJc","components_others_002_002.md":"CAl0oCCy","cssstudy_overflow.md":"y2pjA90_","components_button_theme.md":"t2NZdFND","components_theme.md":"ejkD4gsk","components_button_levitationanimation_002_002.md":"2jd2vqAN","components_button_onclick_001_001.md":"BiodsWe_","components_loading_progress_001_001.md":"usmX7oEH","components_button_levitationanimation_003_003.md":"bQbsHDtu","components_switch_index.md":"SRD6F0UW","components_popover_drawer_index.md":"S4iljoHG","components_text_theme.md":"rQw_V173","components_others_003_003.md":"eIBA0eYL","components_card_002_002.md":"DTtlrt90","components_button_levitationanimation_004_004.md":"q74QugE1","components_menu_theme.md":"H2djhmf8","components_button_levitationanimation_index.md":"F_YtaV4f","components_switch_001_001.md":"Xm0BbpjO","htmlstudy.md":"CS3JDFNO","components_loading_loading_index.md":"u0wXODFx","index.md":"40I7wdkr","components_others_001_001.md":"fI6qJq06","htmlstudy_test1.md":"Jq3I5QCX","components_menu_002_002.md":"Kb7fvzct","components_loading_loading_002_002.md":"uSdnto_z","components_others_index.md":"7quxe0Uq","components_loading_progress_index.md":"AhOg9mK2","components_popover_drawer_001_001.md":"M4C5La9y","components_loading_loading_001_001.md":"fZMCGhOS","components_menu_003_003.md":"7ghslKRQ","components_menu_index.md":"oQCKgu7b","components_text_index.md":"f6iRIPq-"}
